odoo/addons/ssi_print_mixin/README.rst
odoo/addons/ssi_print_mixin/__init__.py
odoo/addons/ssi_print_mixin/__manifest__.py
odoo/addons/ssi_print_mixin/i18n/ssi_print_mixin.pot
odoo/addons/ssi_print_mixin/models/__init__.py
odoo/addons/ssi_print_mixin/models/ir_actions_report.py
odoo/addons/ssi_print_mixin/models/mixin_print_document.py
odoo/addons/ssi_print_mixin/models/print_document_type.py
odoo/addons/ssi_print_mixin/security/ir.model.access.csv
odoo/addons/ssi_print_mixin/static/description/icon.png
odoo/addons/ssi_print_mixin/static/description/index.html
odoo/addons/ssi_print_mixin/static/img/bug.png
odoo/addons/ssi_print_mixin/static/img/circuit.png
odoo/addons/ssi_print_mixin/static/img/download.png
odoo/addons/ssi_print_mixin/static/img/info.png
odoo/addons/ssi_print_mixin/static/img/medal.png
odoo/addons/ssi_print_mixin/static/img/questions.png
odoo/addons/ssi_print_mixin/static/img/workflow.png
odoo/addons/ssi_print_mixin/templates/mixin_print_templates.xml
odoo/addons/ssi_print_mixin/views/ir_actions_report_views.xml
odoo/addons/ssi_print_mixin/views/print_document_type_views.xml
odoo/addons/ssi_print_mixin/wizards/__init__.py
odoo/addons/ssi_print_mixin/wizards/base_print_document.py
odoo/addons/ssi_print_mixin/wizards/base_print_document.xml
odoo_addon_ssi_print_mixin-18.0.1.0.2.1.dist-info/METADATA
odoo_addon_ssi_print_mixin-18.0.1.0.2.1.dist-info/WHEEL
odoo_addon_ssi_print_mixin-18.0.1.0.2.1.dist-info/top_level.txt
odoo_addon_ssi_print_mixin-18.0.1.0.2.1.dist-info/RECORD
